gb_21_11/__init__.py
gb_21_11/app.py
gb_21_11/finder.py
gb_21_11/finder_ui.py
gb_2021.11-0.1.dist-info/METADATA
gb_2021.11-0.1.dist-info/WHEEL
gb_2021.11-0.1.dist-info/entry_points.txt
gb_2021.11-0.1.dist-info/top_level.txt
gb_2021.11-0.1.dist-info/RECORD
